{
  "id": "8e13c7ca-165a-46e9-920c-7c153700c7aa",
  "prevId": "00000000-0000-0000-0000-000000000000",
  "version": "7",
  "dialect": "postgresql",
  "tables": {
    "public.accounts": {
      "name": "accounts",
      "schema": "",
      "columns": {
        "id": {
          "name": "id",
          "type": "uuid",
          "primaryKey": true,
          "notNull": true,
          "default": "gen_random_uuid()"
        },
        "user_id": {
          "name": "user_id",
          "type": "varchar",
          "primaryKey": false,
          "notNull": true
        },
        "account_number": {
          "name": "account_number",
          "type": "varchar",
          "primaryKey": false,
          "notNull": true
        },
        "balance": {
          "name": "balance",
          "type": "numeric(18, 2)",
          "primaryKey": false,
          "notNull": false,
          "default": "'0.00'"
        },
        "created_at": {
          "name": "created_at",
          "type": "timestamp",
          "primaryKey": false,
          "notNull": false,
          "default": "now()"
        }
      },
      "indexes": {},
      "foreignKeys": {},
      "compositePrimaryKeys": {},
      "uniqueConstraints": {
        "accounts_account_number_unique": {
          "name": "accounts_account_number_unique",
          "nullsNotDistinct": false,
          "columns": [
            "account_number"
          ]
        }
      },
      "policies": {},
      "checkConstraints": {},
      "isRLSEnabled": false
    },
    "public.transactions": {
      "name": "transactions",
      "schema": "",
      "columns": {
        "id": {
          "name": "id",
          "type": "uuid",
          "primaryKey": true,
          "notNull": true,
          "default": "gen_random_uuid()"
        },
        "reference": {
          "name": "reference",
          "type": "varchar",
          "primaryKey": false,
          "notNull": true
        },
        "description": {
          "name": "description",
          "type": "varchar",
          "primaryKey": false,
          "notNull": false
        },
        "amount": {
          "name": "amount",
          "type": "numeric(18, 2)",
          "primaryKey": false,
          "notNull": true
        },
        "status": {
          "name": "status",
          "type": "varchar",
          "primaryKey": false,
          "notNull": false,
          "default": "'PENDING'"
        },
        "created_at": {
          "name": "created_at",
          "type": "timestamp",
          "primaryKey": false,
          "notNull": false,
          "default": "now()"
        }
      },
      "indexes": {},
      "foreignKeys": {},
      "compositePrimaryKeys": {},
      "uniqueConstraints": {
        "transactions_reference_unique": {
          "name": "transactions_reference_unique",
          "nullsNotDistinct": false,
          "columns": [
            "reference"
          ]
        }
      },
      "policies": {},
      "checkConstraints": {},
      "isRLSEnabled": false
    },
    "public.ledger_entries": {
      "name": "ledger_entries",
      "schema": "",
      "columns": {
        "id": {
          "name": "id",
          "type": "uuid",
          "primaryKey": true,
          "notNull": true,
          "default": "gen_random_uuid()"
        },
        "transaction_id": {
          "name": "transaction_id",
          "type": "uuid",
          "primaryKey": false,
          "notNull": true
        },
        "account_id": {
          "name": "account_id",
          "type": "uuid",
          "primaryKey": false,
          "notNull": true
        },
        "debit": {
          "name": "debit",
          "type": "numeric(18, 2)",
          "primaryKey": false,
          "notNull": false,
          "default": "'0.00'"
        },
        "credit": {
          "name": "credit",
          "type": "numeric(18, 2)",
          "primaryKey": false,
          "notNull": false,
          "default": "'0.00'"
        },
        "balance_after": {
          "name": "balance_after",
          "type": "numeric(18, 2)",
          "primaryKey": false,
          "notNull": true
        },
        "created_at": {
          "name": "created_at",
          "type": "timestamp",
          "primaryKey": false,
          "notNull": false,
          "default": "now()"
        }
      },
      "indexes": {},
      "foreignKeys": {},
      "compositePrimaryKeys": {},
      "uniqueConstraints": {},
      "policies": {},
      "checkConstraints": {},
      "isRLSEnabled": false
    }
  },
  "enums": {},
  "schemas": {},
  "sequences": {},
  "roles": {},
  "policies": {},
  "views": {},
  "_meta": {
    "columns": {},
    "schemas": {},
    "tables": {}
  }
}